parallel_simulations/__init__.py
parallel_simulations/models.py
parallel_simulations/parallel_simulations.py
parallel_simulations/utils.py
parallel_simulations-0.0.1.dist-info/LICENSE
parallel_simulations-0.0.1.dist-info/METADATA
parallel_simulations-0.0.1.dist-info/WHEEL
parallel_simulations-0.0.1.dist-info/top_level.txt
parallel_simulations-0.0.1.dist-info/RECORD
